eval_suite/__init__.py
eval_suite/cli.py
eval_suite/logging.py
eval_suite/metrics.py
eval_suite/utils.py
eval_suite/benchs/__init__.py
eval_suite/benchs/base_dataset.py
eval_suite/benchs/base_evaluator.py
eval_suite/benchs/ceval/README.md
eval_suite/benchs/ceval/dataset.py
eval_suite/benchs/ceval/eval_ceval.py
eval_suite/benchs/ceval/subject_mapping.json
eval_suite/benchs/ceval/utils.py
eval_suite/benchs/exampleqa/README.md
eval_suite/benchs/exampleqa/dataset.py
eval_suite/benchs/exampleqa/dataset_exampleqa.jsonl
eval_suite/benchs/exampleqa/eval_exampleqa.py
eval_suite/benchs/halluqa/README.md
eval_suite/benchs/halluqa/dataset.py
eval_suite/benchs/halluqa/dataset_halluqa.json
eval_suite/benchs/halluqa/dataset_halluqa_mc.json
eval_suite/benchs/halluqa/eval_base.py
eval_suite/benchs/halluqa/eval_halluqa_mc.py
eval_suite/benchs/halueval/README.md
eval_suite/benchs/halueval/dataset.py
eval_suite/benchs/halueval/dataset_halueval_dialogue.jsonl
eval_suite/benchs/halueval/dataset_halueval_qa.jsonl
eval_suite/benchs/halueval/dataset_halueval_summarization.jsonl
eval_suite/benchs/halueval/eval_base.py
eval_suite/benchs/halueval/eval_halueval_dialog.py
eval_suite/benchs/halueval/eval_halueval_qa.py
eval_suite/benchs/halueval/eval_halueval_summa.py
eval_suite/benchs/uhgeval/README.md
eval_suite/benchs/uhgeval/dataset.py
eval_suite/benchs/uhgeval/dataset_uhgeval_concise.jsonl
eval_suite/benchs/uhgeval/dataset_uhgeval_full.jsonl
eval_suite/benchs/uhgeval/eval_base.py
eval_suite/benchs/uhgeval/eval_disc_keyword.py
eval_suite/benchs/uhgeval/eval_disc_sentence.py
eval_suite/benchs/uhgeval/eval_gene.py
eval_suite/benchs/uhgeval/eval_sele.py
eval_suite/llms/__init__.py
eval_suite/llms/base_llm.py
eval_suite/llms/huggingface.py
eval_suite/llms/openai_api.py
eval_suite-2.1.4.dist-info/METADATA
eval_suite-2.1.4.dist-info/WHEEL
eval_suite-2.1.4.dist-info/entry_points.txt
eval_suite-2.1.4.dist-info/licenses/LICENSE
eval_suite-2.1.4.dist-info/RECORD
