Metadata-Version: 2.3
Name: eval_suite
Version: 2.1.4
Summary: User-friendly evaluation framework: Eval Suite & Benchmarks: UHGEval, HaluEval, HalluQA, etc.
Project-URL: Repository, https://github.com/IAAR-Shanghai/UHGEval
Author-email: Shichao Song <songshichao517@gmail.com>
License:                                  Apache License
Keywords: Chinese,UHGEval,eval_suite,evaluation,hallucination,llm
Classifier: License :: OSI Approved :: Apache Software License
Classifier: Operating System :: OS Independent
Classifier: Programming Language :: Python :: 3.10
Classifier: Programming Language :: Python :: 3.11
Classifier: Programming Language :: Python :: 3.12
Requires-Python: >=3.10
Requires-Dist: absl-py
Requires-Dist: accelerate
Requires-Dist: black
Requires-Dist: ipykernel
Requires-Dist: isort
Requires-Dist: nltk
Requires-Dist: openai
Requires-Dist: rouge-score
Requires-Dist: sentencepiece
Requires-Dist: tenacity
Requires-Dist: text2vec
Requires-Dist: torch
Requires-Dist: tqdm
Requires-Dist: transformers
